flask_allowed_hosts/__init__.py
flask_allowed_hosts/allowed_hosts.py
flask_allowed_hosts/helpers.py
flask_allowed_hosts/logger.py
flask_allowed_hosts/permission_manager.py
flask_allowed_hosts/validators.py
flask_allowed_hosts-1.2.0.dist-info/LICENSE.md
flask_allowed_hosts-1.2.0.dist-info/METADATA
flask_allowed_hosts-1.2.0.dist-info/WHEEL
flask_allowed_hosts-1.2.0.dist-info/top_level.txt
flask_allowed_hosts-1.2.0.dist-info/RECORD
