Metadata-Version: 2.1
Name: flask-allowed-hosts
Version: 1.2.0
Summary: A Flask extension to limit access to your routes by using allowed hostnames and IP addresses.
Home-page: https://github.com/riad-azz/flask-allowed-hosts
Author: Riadh Azzoun
Author-email: riadh.azzoun@hotmail.com
License: MIT
Keywords: flask,allowed hosts,web development,security,flask extension,ip validation,host validation,hostnames validation
Classifier: Development Status :: 5 - Production/Stable
Classifier: Intended Audience :: Developers
Classifier: License :: OSI Approved :: MIT License
Classifier: Programming Language :: Python
Classifier: Topic :: Software Development :: Libraries :: Python Modules
Classifier: Topic :: Internet :: WWW/HTTP :: Dynamic Content
Classifier: Topic :: Internet :: WWW/HTTP :: WSGI :: Application
Classifier: Topic :: Security
Classifier: Operating System :: OS Independent
License-File: LICENSE.md
Requires-Dist: Flask
